cyberops/__init__.py
cyberops/scan.py
cyberops-0.1.0.dist-info/LICENSE
cyberops-0.1.0.dist-info/METADATA
cyberops-0.1.0.dist-info/WHEEL
cyberops-0.1.0.dist-info/top_level.txt
cyberops-0.1.0.dist-info/RECORD
